flaskapptest/__init__.py
flaskapptest/cli/__init__.py
flaskapptest/cli/batch_runner.py
flaskapptest/cli/ci_runner.py
flaskapptest/cli/main.py
flaskapptest/cli/manual_runner.py
flaskapptest/core/__init__.py
flaskapptest/core/endpoint_extractor.py
flaskapptest/core/flask_detector.py
flaskapptest/core/payload_generator.py
flaskapptest/core/project_scanner.py
flaskapptest/core/reporting.py
flaskapptest/core/request_executor.py
flaskapptest/core/schema_extractor.py
flaskapptest/core/test_generator.py
flaskapptest/core/test_runner.py
flaskapptest/core/validators.py
flaskapptest/tests/test_endpoint_extractor.py
flaskapptest/tests/test_flask_detector.py
flaskapptest/tests/test_payload_generator.py
flaskapptest/tests/test_project_scanner.py
flaskapptest/tests/test_reporting.py
flaskapptest/tests/test_request_executor.py
flaskapptest/tests/test_schema_extractor.py
flaskapptest/tests/test_test_generator.py
flaskapptest/tests/test_test_runner.py
flaskapptest/tests/test_validators.py
flaskapptest-2.0.0.dist-info/licenses/LICENSE
flaskapptest-2.0.0.dist-info/METADATA
flaskapptest-2.0.0.dist-info/WHEEL
flaskapptest-2.0.0.dist-info/entry_points.txt
flaskapptest-2.0.0.dist-info/top_level.txt
flaskapptest-2.0.0.dist-info/RECORD
