Metadata-Version: 2.4
Name: flaskapptest
Version: 2.0.0
Summary: Production-grade Flask API testing CLI
Author-email: Ganesh Nalawade <ganesh@example.com>
License-Expression: MIT
Requires-Python: >=3.9
License-File: LICENSE
Requires-Dist: requests
Requires-Dist: pytest
Dynamic: license-file
